{
  "id": "Банк",
  "lang": "fr",
  "sections": [
    {
      "title": "Ouvrir un compte / Ouvrir une compte bancaire",
      "content": "ABRIR UNA CUENTA BANCARIA / OUVERTURE D'UN COMPTE BANCAIRE\n\nLes étudiants étrangers peuvent ouvrir des comptes et des tarifs en bancos russes\n(Sberbank, Tinkoff, VTB, Alfa-Bank).\n\nDOCUMENTOS / DOCUMENTS :\n- Pasaporte con traducción notarial / Passeport avec traduction notariée\n- Visa y tarjeta de migración / Visa et carte de migration\n- Registro migratorio / Enregistrement des migrations\n- Numéro d'identification fiscale (NIF)\n- Certificado de estudios de KubGU / Certificat de KubGU\n\nTARJETA / MAP: World (sistema nacional) recommandé aux étudiants.\nLes tarjetas Visa/Mastercard étrangères ne peuvent pas fonctionner en Russie.\nLes cartes Visa/Mastercard étrangères peuvent ne pas fonctionner en Russie."
    },
    {
      "title": "Paiement et virements / Pagos y transferencias",
      "content": "PAGOS Y TRANSFERENCIAS / PAIEMENTS ET TRANSFERTS\n\n- Pago por SBP (Fast Payment System) avec numéro de téléphone / Paiement via SBP\n- Applicación móvil del banco / Application mobile bancaire\n- Pago de la résidence y matrícula / Paiement de l'auberge et des frais de scolarité\n- Transferencias entre tarjetas World / Transferts entre cartes Monde\n\nCONSEJO / CONSEIL : activer les notifications SMS / Activer les notifications SMS"
    }
  ]
}