{
  "id": "Банк",
  "lang": "vi",
  "sections": [
    {
      "title": "Mở tài khoản / Abrir una cuente bancaria",
      "content": "ABRIR UNA CUENTA BANCARIA / MỞ TÀI KHOẢN NGÂN HÀNG\n\nLos estudiantes extranjeros pueden abrir cuenta và tarjeta en bancos rusos\n(Sberbank, Tinkoff, VTB, Alfa-Bank).\n\nTÀI LIỆU/TÀI LIỆU:\n- Pasaporte con traducción công chứng / Hộ chiếu có dịch thuật công chứng\n- Visa y tarjeta de migración / Visa và thẻ di trú\n- Đăng ký di chuyển / Đăng ký di chuyển\n- Mã số người nộp thuế (TIN)\n- Chứng chỉ estudios de KubGU / Chứng chỉ từ KubGU\n\nTARJETA / MAP: Thế giới (hệ thống quốc gia) được giới thiệu dành cho sinh viên.\nCác thẻ mở rộng Visa/Mastercard không còn chức năng ở Nga.\nVisa/Mastercard nước ngoài có thể không hoạt động ở Nga."
    },
    {
      "title": "Thanh toán và chuyển khoản / Trang và chuyển khoản",
      "content": "PAGOS Y CHUYỂN NHƯỢNG / THANH TOÁN VÀ CHUYỂN NHƯỢNG\n\n- Pago por SBP (Hệ thống thanh toán nhanh) với số điện thoại / Thanh toán qua SBP\n- Ứng dụng di động móvil del banco / Ứng dụng di động ngân hàng\n- Pago de la residcia y matrícula / Thanh toán tiền ký túc xá và học phí\n- Chuyển khoản trong thế giới tarjetas / Chuyển giữa các thẻ Thế giới\n\nCONSEJO / TIP: kích hoạt thông báo SMS / Bật thông báo SMS"
    }
  ]
}